dmri_commit-2.4.1.dist-info/METADATA
dmri_commit-2.4.1.dist-info/top_level.txt
dmri_commit-2.4.1.dist-info/WHEEL
dmri_commit-2.4.1.dist-info/RECORD
dmri_commit-2.4.1.dist-info/licenses/LICENSE
commit/proximals.cpython-39-aarch64-linux-gnu.so
commit/core.cpython-39-aarch64-linux-gnu.so
commit/solvers.py
commit/__init__.py
commit/models.cpython-39-aarch64-linux-gnu.so
commit/trk2dictionary.cpython-39-aarch64-linux-gnu.so
commit/operator/operator_c.c
commit/operator/operator.pyx
commit/operator/__init__.py
commit/operator/operator.cpython-39-aarch64-linux-gnu.so
