Metadata-Version: 2.4
Name: dmri-commit
Version: 2.4.1
Summary: Convex Optimization Modeling for Microstructure Informed Tractography (COMMIT)
Author-email: Alessandro Daducci <alessandro.daducci@univr.it>
Maintainer-email: DICE lab <DICE_lab@strutture.univr.it>
License: ################################################################################
Project-URL: Homepage, https://github.com/daducci/COMMIT.git
Project-URL: Documentation, https://github.com/daducci/COMMIT/wiki
Project-URL: Repository, https://github.com/daducci/COMMIT.git
Project-URL: Issues, https://github.com/daducci/COMMIT/issues
Project-URL: Changelog, https://github.com/daducci/COMMIT/blob/master/CHANGELOG.md
Keywords: Neuroimaging
Classifier: Intended Audience :: Science/Research
Classifier: License :: Other/Proprietary License
Classifier: Programming Language :: C++
Classifier: Programming Language :: Cython
Classifier: Programming Language :: Python :: 3
Classifier: Programming Language :: Python :: 3 :: Only
Classifier: Programming Language :: Python :: 3.8
Classifier: Programming Language :: Python :: 3.9
Classifier: Programming Language :: Python :: 3.10
Classifier: Programming Language :: Python :: 3.11
Classifier: Programming Language :: Python :: 3.12
Requires-Python: >=3.8
License-File: LICENSE
Requires-Dist: dmri-amico>=2.0.1
Requires-Dist: dmri-dicelib>=1.1.0
Requires-Dist: numpy<2.0.0,>=1.24.4
Requires-Dist: scipy>=1.10.1
Dynamic: license-file
